[
  {
    "id": "vw-amarok-trendline-140cv-0km",
    "name": "Vw Amarok Trendline 140cv",
    "marca": "Volkswagen",
    "marcaId": "volkswagen",
    "ano": 2025,
    "kilometraje": 0,
    "precio": {
      "valor": 999999,
      "moneda": "ARS"
    },
    "categoria": "Pickup",
    "transmision": "Manual",
    "motor": "2.0",
    "combustible": "Diésel",
    "puertas": 4,
    "images": [
      "1-1.webp",
      "1-2.webp",
      "1-3.webp",
      "1-4.webp",
      "1-5.webp",
      "1-6.webp",
      "1-7.webp"
    ],
    "descripcion": "Vw Amarok Trendline 140cv.\n\n0km.\n\nEntrega inmediata."
  },
  {
    "id": "toyota-corolla-seg-0km",
    "name": "Toyota Corolla Seg",
    "marca": "Toyota",
    "marcaId": "toyota",
    "ano": 2025,
    "kilometraje": 0,
    "precio": {
      "valor": 999999,
      "moneda": "ARS"
    },
    "categoria": "Sedan",
    "transmision": "Automática",
    "motor": "2.0",
    "combustible": "Nafta",
    "puertas": 4,
    "images": [
      "2-1.webp",
      "2-2.webp",
      "2-3.webp",
      "2-4.webp",
      "2-5.webp",
      "2-6.webp",
      "2-7.webp",
      "2-8.webp"
    ],
    "descripcion": "Toyota Corolla SEG.\n\n0km.\n\nEntrega inmediata."
  },
  {
    "id": "ford-ranger-limited-2021",
    "name": "Ford Ranger Limited",
    "marca": "Ford",
    "marcaId": "ford",
    "ano": 2021,
    "kilometraje": 115000,
    "precio": {
      "valor": 999999,
      "moneda": "ARS"
    },
    "categoria": "Pickup",
    "transmision": "Automática",
    "motor": "3.2",
    "combustible": "Diésel",
    "puertas": 4,
    "images": [
      "3-1.webp",
      "3-2.webp",
      "3-3.webp",
      "3-4.webp",
      "3-5.webp",
      "3-6.webp",
      "3-7.webp"
    ],
    "descripcion": "Ford Ranger Limited.\n\nMod. 2021.\n\n115.000 kms."
  },
  {
    "id": "ford-bronco-wildtrak-2022",
    "name": "Ford Bronco Wildtrak",
    "marca": "Ford",
    "marcaId": "ford",
    "ano": 2022,
    "kilometraje": 89000,
    "precio": {
      "valor": 999999,
      "moneda": "ARS"
    },
    "categoria": "SUV",
    "transmision": "Automática",
    "motor": "2.3",
    "combustible": "Nafta",
    "puertas": 5,
    "images": [
      "4-1.webp",
      "4-2.webp",
      "4-3.webp",
      "4-4.webp",
      "4-5.webp",
      "4-6.webp",
      "4-7.webp",
      "4-8.webp"
    ],
    "descripcion": "Ford Bronco Wildtrak.\n\nMod. 2022.\n\n89.000 kms."
  },
  {
    "id": "chevrolet-cruze-rs-2022",
    "name": "Chevrolet Cruze Rs",
    "marca": "Chevrolet",
    "marcaId": "chevrolet",
    "ano": 2022,
    "kilometraje": 41000,
    "precio": {
      "valor": 999999,
      "moneda": "ARS"
    },
    "categoria": "Sedan",
    "transmision": "Automática",
    "motor": "1.4",
    "combustible": "Nafta",
    "puertas": 4,
    "images": [
      "5-1.webp",
      "5-2.webp",
      "5-3.webp",
      "5-4.webp",
      "5-5.webp",
      "5-6.webp",
      "5-7.webp",
      "5-8.webp",
      "5-9.webp"
    ],
    "descripcion": "Chevrolet Cruze RS.\n\nMod. 2022.\n\n41.000 kms."
  },
  {
    "id": "vw-amarok-v6-comfortline-2021",
    "name": "Vw Amarok V6 Comfortline",
    "marca": "Volkswagen",
    "marcaId": "volkswagen",
    "ano": 2021,
    "kilometraje": 125000,
    "precio": {
      "valor": 999999,
      "moneda": "ARS"
    },
    "categoria": "Pickup",
    "transmision": "Automática",
    "motor": "3.0",
    "combustible": "Diésel",
    "puertas": 4,
    "images": [
      "6-1.webp",
      "6-2.webp",
      "6-3.webp",
      "6-4.webp",
      "6-5.webp",
      "6-6.webp",
      "6-7.webp"
    ],
    "descripcion": "Vw Amarok V6 Comfortline.\n\nMod. 2021.\n\n125.000 kms."
  },
  {
    "id": "vw-amarok-v6-comfortline-2020",
    "name": "Vw Amarok V6 Comfortline",
    "marca": "Volkswagen",
    "marcaId": "volkswagen",
    "ano": 2020,
    "kilometraje": 80000,
    "precio": {
      "valor": 999999,
      "moneda": "ARS"
    },
    "categoria": "Pickup",
    "transmision": "Automática",
    "motor": "3.0",
    "combustible": "Diésel",
    "puertas": 4,
    "images": [
      "7-1.webp",
      "7-2.webp",
      "7-3.webp",
      "7-4.webp",
      "7-5.webp",
      "7-6.webp",
      "7-7.webp",
      "7-8.webp"
    ],
    "descripcion": "Vw Amarok V6 Comfortline.\n\nMod. 2020.\n\n80.000 kms."
  },
  {
    "id": "jeep-renegade-sport-2018",
    "name": "Jeep Renegade Sport",
    "marca": "Jeep",
    "marcaId": "jeep",
    "ano": 2018,
    "kilometraje": 129000,
    "precio": {
      "valor": 999999,
      "moneda": "ARS"
    },
    "categoria": "SUV",
    "transmision": "Manual",
    "motor": "1.8",
    "combustible": "Nafta",
    "puertas": 5,
    "images": [
      "8-1.webp",
      "8-2.webp",
      "8-3.webp",
      "8-4.webp",
      "8-5.webp",
      "8-6.webp",
      "8-7.webp"
    ],
    "descripcion": "Jeep Renegade Sport.\n\nMod. 2018.\n\n129.000 kms."
  },
  {
    "id": "vw-amarok-v6-extreme-0km",
    "name": "Vw Amarok V6 Extreme",
    "marca": "Volkswagen",
    "marcaId": "volkswagen",
    "ano": 2025,
    "kilometraje": 0,
    "precio": {
      "valor": 999999,
      "moneda": "ARS"
    },
    "categoria": "Pickup",
    "transmision": "Automática",
    "motor": "3.0",
    "combustible": "Diésel",
    "puertas": 4,
    "images": [
      "9-1.webp",
      "9-2.webp",
      "9-3.webp",
      "9-4.webp",
      "9-5.webp",
      "9-6.webp",
      "9-7.webp",
      "9-8.webp",
      "9-9.webp",
      "9-10.webp",
      "9-11.webp",
      "9-12.webp",
      "9-13.webp"
    ],
    "descripcion": "Vw Amarok V6 Extreme.\n\n0km.\n\nEntrega inmediata."
  },
  {
    "id": "renault-kardian-techno-0km",
    "name": "Renault Kardian Techno",
    "marca": "Renault",
    "marcaId": "renault",
    "ano": 2025,
    "kilometraje": 0,
    "precio": {
      "valor": 999999,
      "moneda": "ARS"
    },
    "categoria": "SUV",
    "transmision": "Automática",
    "motor": "1.0",
    "combustible": "Nafta",
    "puertas": 5,
    "images": [
      "10-1.webp",
      "10-2.webp",
      "10-3.webp",
      "10-4.webp",
      "10-5.webp",
      "10-6.webp",
      "10-7.webp",
      "10-8.webp"
    ],
    "descripcion": "Renault Kardian Techno.\n\n0km.\n\nEntrega inmediata."
  },
  {
    "id": "citroen-c4-cactus-shine-2025",
    "name": "Citroën C4 Cactus Shine",
    "marca": "Citroën",
    "marcaId": "citroen",
    "ano": 2025,
    "kilometraje": 2500,
    "precio": {
      "valor": 999999,
      "moneda": "ARS"
    },
    "categoria": "SUV",
    "transmision": "Automática",
    "motor": "1.6",
    "combustible": "Nafta",
    "puertas": 5,
    "images": [
      "11-1.webp",
      "11-2.webp",
      "11-3.webp",
      "11-4.webp",
      "11-5.webp",
      "11-6.webp",
      "11-7.webp",
      "11-8.webp",
      "11-9.webp"
    ],
    "descripcion": "Citroën C4 Cactus Shine.\n\nMod. 2025.\n\n2.500 kms."
  },
  {
    "id": "vw-amarok-v6-highline-2022",
    "name": "Vw Amarok V6 Highline",
    "marca": "Volkswagen",
    "marcaId": "volkswagen",
    "ano": 2022,
    "kilometraje": 187000,
    "precio": {
      "valor": 999999,
      "moneda": "ARS"
    },
    "categoria": "Pickup",
    "transmision": "Automática",
    "motor": "3.0",
    "combustible": "Diésel",
    "puertas": 4,
    "images": [
      "12-1.webp",
      "12-2.webp",
      "12-3.webp",
      "12-4.webp",
      "12-5.webp",
      "12-6.webp",
      "12-7.webp",
      "12-8.webp",
      "12-9.webp"
    ],
    "descripcion": "Vw Amarok V6 Highline.\n\nMod. 2022.\n\n187.000 kms."
  }
]
